setup.py
ejercicio13/__init__.py
ejercicio13/operaciones.py
ejercicio13_operaciones.egg-info/PKG-INFO
ejercicio13_operaciones.egg-info/SOURCES.txt
ejercicio13_operaciones.egg-info/dependency_links.txt
ejercicio13_operaciones.egg-info/requires.txt
ejercicio13_operaciones.egg-info/top_level.txt