Metadata-Version: 2.4
Name: ejercicio13_operaciones
Version: 0.5
Summary: Libreria de mates
Home-page: https://github.com/JuanLuisMorales/libreria_rc
Download-URL: https://github.com/JuanLuisMorales/libreria_rc.git
Author: Juan Luis
Author-email: juanlumm19@gmail.com
License: MIT
Keywords: suma,resta,multiplicacion,division
Classifier: Development Status :: 3 - Alpha
Classifier: Intended Audience :: Developers
Classifier: Topic :: Software Development :: Build Tools
Classifier: License :: OSI Approved :: MIT License
Classifier: Programming Language :: Python :: 3
Classifier: Programming Language :: Python :: 3.4
Classifier: Programming Language :: Python :: 3.5
Classifier: Programming Language :: Python :: 3.6
Requires-Dist: pytest
Dynamic: author
Dynamic: author-email
Dynamic: classifier
Dynamic: download-url
Dynamic: home-page
Dynamic: keywords
Dynamic: license
Dynamic: requires-dist
Dynamic: summary
